statadict/__init__.py
statadict/base.py
tests/__init__.py
tests/test_parse_stata_dict.py
tests/resources/2017_2019_FemPregSetup.dct
statadict-1.1.0.dist-info/LICENSE
statadict-1.1.0.dist-info/METADATA
statadict-1.1.0.dist-info/WHEEL
statadict-1.1.0.dist-info/top_level.txt
statadict-1.1.0.dist-info/RECORD
