Metadata-Version: 2.1
Name: statadict
Version: 1.1.0
Summary: Utility for parsing Stata dictionary files for usage with Pandas.
Home-page: https://github.com/atudomain/statadict
Author: Adrian Tuzimek
Author-email: tuziomek@gmail.com
License: UNKNOWN
Keywords: pandas,stata,dictionary,parse,import
Platform: UNKNOWN
Classifier: Programming Language :: Python :: 3 :: Only
Classifier: License :: OSI Approved :: BSD License
Classifier: Operating System :: POSIX :: Linux
Classifier: Environment :: Console
Classifier: Intended Audience :: Developers
Classifier: Intended Audience :: System Administrators
Classifier: Intended Audience :: Information Technology
